distorage/__init__.py
distorage/_vars.py
distorage/common_server.py
distorage/custom_server.py
distorage/errors.py
distorage-2.0.0.dist-info/LICENSE
distorage-2.0.0.dist-info/METADATA
distorage-2.0.0.dist-info/WHEEL
distorage-2.0.0.dist-info/top_level.txt
distorage-2.0.0.dist-info/RECORD
