Metadata-Version: 2.1
Name: distorage
Version: 2.0.0
Summary: The system to host your files on the Discord application
Home-page: https://github.com/Sellig6792/Distorage.py
Author: Sellig6792
Author-email: sellig.dev@gmail.com
License: MIT
Keywords: discord,storage,file,hosting,upload,server
Platform: UNKNOWN
Classifier: Programming Language :: Python :: 3
Classifier: License :: OSI Approved :: MIT License
Classifier: Operating System :: OS Independent
Requires-Python: >=3.6
License-File: LICENSE
Requires-Dist: requests (~=2.26.0)
